LICENSE.txt
MANIFEST.in
README.rst
requirements.txt
setup.py
docs/Makefile
docs/build/doctrees/environment.pickle
docs/build/doctrees/index.doctree
docs/build/doctrees/modules/tabular.colors.doctree
docs/build/doctrees/modules/tabular.fast.doctree
docs/build/doctrees/modules/tabular.io.doctree
docs/build/doctrees/modules/tabular.spreadsheet.doctree
docs/build/doctrees/modules/tabular.tab.doctree
docs/build/doctrees/modules/tabular.utils.doctree
docs/build/doctrees/modules/tabular.web.doctree
docs/build/doctrees/reference/construction.doctree
docs/build/doctrees/reference/fastops.doctree
docs/build/doctrees/reference/hierarchical.doctree
docs/build/doctrees/reference/io.doctree
docs/build/doctrees/reference/operations.doctree
docs/build/doctrees/reference/organization.doctree
docs/build/doctrees/reference/quickstart.doctree
docs/build/doctrees/reference/web.doctree
docs/build/doctrees/reference/data/example_color.hsv/header.doctree
docs/build/doctrees/reference/data/example_color.hsv/info.hsv/header.doctree
docs/build/doctrees/reference/data/example_color.hsv/price.hsv/header.doctree
docs/build/doctrees/reference/data/example_nocolor.hsv/header.doctree
docs/build/html/.buildinfo
docs/build/html/genindex.html
docs/build/html/index.html
docs/build/html/objects.inv
docs/build/html/py-modindex.html
docs/build/html/search.html
docs/build/html/searchindex.js
docs/build/html/_images/example.png
docs/build/html/_images/example_color_xls.png
docs/build/html/_images/organization.png
docs/build/html/_sources/index.txt
docs/build/html/_sources/modules/tabular.colors.txt
docs/build/html/_sources/modules/tabular.fast.txt
docs/build/html/_sources/modules/tabular.io.txt
docs/build/html/_sources/modules/tabular.spreadsheet.txt
docs/build/html/_sources/modules/tabular.tab.txt
docs/build/html/_sources/modules/tabular.utils.txt
docs/build/html/_sources/modules/tabular.web.txt
docs/build/html/_sources/reference/construction.txt
docs/build/html/_sources/reference/fastops.txt
tabular.egg-info/PKG-INFO
tabular.egg-info/SOURCES.txt
tabular.egg-info/dependency_links.txt
tabular.egg-info/requires.txt
tabular.egg-info/top_level.txt
