Metadata-Version: 1.0
Name: tabular
Version: 0.1
Summary: Tabular data container and associated convenience routines in Python
Home-page: http://github.com/yamins81/tabular
Author: Elaine Angelino and Daniel Yamins
Author-email: yamins@mit.edu
License: UNKNOWN
Platform: UNKNOWN
Classifier: Development Status :: 4 - Beta
Classifier: License :: OSI Approved :: MIT License
Classifier: Topic :: Scientific/Engineering :: Information Analysis
